[
    {
        "author": "SaChiA5566",
        "date": " 3/20",
        "href": "https://www.ptt.cc/bbs/NBA/M.1710910488.A.982.html",
        "push_count": "爆",
        "title": "Re: [花邊] 「把大鯊魚放到現在，他有Jokic強嗎」？"
    },
    {
        "author": "ClownT",
        "date": " 3/20",
        "href": "https://www.ptt.cc/bbs/NBA/M.1710910645.A.978.html",
        "push_count": "73",
        "title": "[花邊] 多名活塞04冠軍成員出席紀念活動"
    },
    {
        "author": "s66449",
        "date": " 3/20",
        "href": "https://www.ptt.cc/bbs/NBA/M.1710910713.A.A39.html",
        "push_count": "9",
        "title": "[新聞] 明星賽後得分下滑　教頭各有不同看法"
    },
    {
        "author": "love1500274",
        "date": " 3/20",
        "href": "https://www.ptt.cc/bbs/NBA/M.1710913068.A.CCE.html",
        "push_count": "35",
        "title": "[花邊] Kyrie灌籃 賽後記者問他會參加灌籃大賽嗎"
    },
    {
        "author": "admeta",
        "date": " 3/20",
        "href": "https://www.ptt.cc/bbs/NBA/M.1710914051.A.2D4.html",
        "push_count": "爆",
        "title": "[新聞] 影／「怪物狀元」威廉森超狂空中接力　"
    },
    {
        "author": "kakala99",
        "date": " 3/20",
        "href": "https://www.ptt.cc/bbs/NBA/M.1710915192.A.6B0.html",
        "push_count": "94",
        "title": "[情報] Green:Kyrie比KD還難防，你找準時機"
    },
    {
        "author": "steven183",
        "date": " 3/20",
        "href": "https://www.ptt.cc/bbs/NBA/M.1710919456.A.5BE.html",
        "push_count": "爆",
        "title": "[花邊] 網路上流傳的嘴綠兒子打小沙兒子是假新聞"
    },
    {
        "author": "dora1024",
        "date": " 3/20",
        "href": "https://www.ptt.cc/bbs/NBA/M.1710923363.A.625.html",
        "push_count": "39",
        "title": "[新聞] 看好溫班亞瑪超越歷屆DPOY 厄文：我喜歡"
    },
    {
        "author": "k7202001",
        "date": " 3/20",
        "href": "https://www.ptt.cc/bbs/NBA/M.1710927083.A.560.html",
        "push_count": "爆",
        "title": "[討論] 本季誰的健康出賽數最讓人意外？"
    },
    {
        "author": "sasayaaa",
        "date": " 3/20",
        "href": "https://www.ptt.cc/bbs/NBA/M.1710931363.A.832.html",
        "push_count": "46",
        "title": "Re: [花邊] 「把大鯊魚放到現在，他有Jokic強嗎」？"
    },
    {
        "author": "TheoEpstein",
        "date": " 3/20",
        "href": "https://www.ptt.cc/bbs/NBA/M.1710935523.A.A53.html",
        "push_count": "21",
        "title": "Re: [討論] 本季誰的健康出賽數最讓人意外？"
    },
    {
        "author": "kerkerson",
        "date": " 3/20",
        "href": "https://www.ptt.cc/bbs/NBA/M.1710936706.A.2FD.html",
        "push_count": "71",
        "title": "[討論] 雷霆的process怎麼比76人強那麼多??"
    },
    {
        "author": "star880613",
        "date": " 3/20",
        "href": "https://www.ptt.cc/bbs/NBA/M.1710941550.A.087.html",
        "push_count": "28",
        "title": "[情報] Giannis將缺席對陣塞爾提克的比賽"
    },
    {
        "author": "amdvega",
        "date": " 3/20",
        "href": "https://www.ptt.cc/bbs/NBA/M.1710943951.A.3BB.html",
        "push_count": "90",
        "title": "Re: [花邊] 「把大鯊魚放到現在，他有Jokic強嗎」？"
    },
    {
        "author": "sampsonlu919",
        "date": " 3/20",
        "href": "https://www.ptt.cc/bbs/NBA/M.1710945545.A.289.html",
        "push_count": "16",
        "title": "[新聞] 退役球星皮爾斯 洛城住家遭竊"
    },
    {
        "author": "thnlkj0665",
        "date": " 3/20",
        "href": "https://www.ptt.cc/bbs/NBA/M.1710947670.A.48E.html",
        "push_count": "45",
        "title": "[情報] Gabe Vincent 接近復出"
    },
    {
        "author": "Wojnarowski",
        "date": " 3/20",
        "href": "https://www.ptt.cc/bbs/NBA/M.1710948431.A.67F.html",
        "push_count": "43",
        "title": "[花邊] LBJ：塞爾提克用一袋薯片換到假日"
    },
    {
        "author": "guardyo",
        "date": " 3/20",
        "href": "https://www.ptt.cc/bbs/NBA/M.1710905701.A.AAD.html",
        "push_count": "31",
        "title": "[情報] NBA Standings (Mar. 20, 2024)"
    },
    {
        "author": "ZIDENS",
        "date": " 3/20",
        "href": "https://www.ptt.cc/bbs/NBA/M.1710906106.A.F96.html",
        "push_count": "4",
        "title": "[公告] NBA 板 開始舉辦樂透!"
    },
    {
        "author": "jason911152",
        "date": " 3/20",
        "href": "https://www.ptt.cc/bbs/NBA/M.1710894623.A.FA0.html",
        "push_count": "爆",
        "title": "[Live] 金塊 @ 灰狼"
    },
    {
        "author": "Rambo",
        "date": " 3/20",
        "href": "https://www.ptt.cc/bbs/NBA/M.1710897256.A.614.html",
        "push_count": "20",
        "title": "[BOX ] Hornets 92:112 Magic 數據"
    },
    {
        "author": "Rambo",
        "date": " 3/20",
        "href": "https://www.ptt.cc/bbs/NBA/M.1710897757.A.9E1.html",
        "push_count": "55",
        "title": "[BOX ] Rockets 137:114 Wizards 數據"
    },
    {
        "author": "murmurs0803",
        "date": " 3/20",
        "href": "https://www.ptt.cc/bbs/NBA/M.1710898359.A.1BA.html",
        "push_count": "96",
        "title": "[花邊] Luka Doncic從後場傳給隊友空接"
    },
    {
        "author": "bengowa",
        "date": " 3/20",
        "href": "https://www.ptt.cc/bbs/NBA/M.1710898574.A.8B6.html",
        "push_count": "60",
        "title": "[外絮] LBJ:2022勇士贏青賽贏在球商"
    },
    {
        "author": "Rambo",
        "date": " 3/20",
        "href": "https://www.ptt.cc/bbs/NBA/M.1710899206.A.806.html",
        "push_count": "51",
        "title": "[BOX ] Pelicans 104:91 Nets 數據"
    },
    {
        "author": "Rambo",
        "date": " 3/20",
        "href": "https://www.ptt.cc/bbs/NBA/M.1710901614.A.2BE.html",
        "push_count": "80",
        "title": "[BOX ] Mavericks 113:107 Spurs 數據"
    },
    {
        "author": "love1500274",
        "date": " 3/20",
        "href": "https://www.ptt.cc/bbs/NBA/M.1710901884.A.A4A.html",
        "push_count": "爆",
        "title": "[情報] Wemby是最具影響力的防守球員"
    },
    {
        "author": "Kazmier",
        "date": " 3/20",
        "href": "https://www.ptt.cc/bbs/NBA/M.1710904245.A.568.html",
        "push_count": "57",
        "title": "[花邊] 杰倫是史上最年輕達成 42分10籃板7三分"
    },
    {
        "author": "Rambo",
        "date": " 3/20",
        "href": "https://www.ptt.cc/bbs/NBA/M.1710905048.A.70E.html",
        "push_count": "爆",
        "title": "[BOX ] Nuggets 115:112 Timberwolves 數據"
    },
    {
        "author": "[彩券]",
        "date": " 3/20",
        "href": "https://www.ptt.cc/bbs/NBA/M.1710905146.A.403.html",
        "push_count": "4",
        "title": "[公告] NBA 樂透開獎"
    },
    {
        "author": "guardyo",
        "date": " 3/20",
        "href": "https://www.ptt.cc/bbs/NBA/M.1710905701.A.AAD.html",
        "push_count": "35",
        "title": "[情報] NBA Standings (Mar. 20, 2024)"
    },
    {
        "author": "LBJnot1to7",
        "date": " 3/20",
        "href": "https://www.ptt.cc/bbs/NBA/M.1710905704.A.A9A.html",
        "push_count": "爆",
        "title": "[花邊] Poole今日被J.Landale賞了5記火鍋"
    },
    {
        "author": "ZIDENS",
        "date": " 3/20",
        "href": "https://www.ptt.cc/bbs/NBA/M.1710906106.A.F96.html",
        "push_count": "7",
        "title": "[公告] NBA 板 開始舉辦樂透!"
    },
    {
        "author": "KyrieIrving1",
        "date": " 3/20",
        "href": "https://www.ptt.cc/bbs/NBA/M.1710907309.A.4DB.html",
        "push_count": "爆",
        "title": "[花邊] 獨行俠為KI配置了私人廚師"
    },
    {
        "author": "zsp9081a",
        "date": " 3/20",
        "href": "https://www.ptt.cc/bbs/NBA/M.1710908009.A.5FF.html",
        "push_count": "55",
        "title": "[討論] 林書豪禁賽事件如果發生在NBA會是怎樣的"
    },
    {
        "author": "dora1024",
        "date": " 3/20",
        "href": "https://www.ptt.cc/bbs/NBA/M.1710908151.A.22D.html",
        "push_count": "46",
        "title": "[花邊] Lamar Odom：以前賽前我會尻一發"
    },
    {
        "author": "z72117211",
        "date": " 3/20",
        "href": "https://www.ptt.cc/bbs/NBA/M.1710908250.A.6D6.html",
        "push_count": "爆",
        "title": "[花邊] 「把大鯊魚放到現在，他有Jokic強嗎」？"
    },
    {
        "author": "hanson90244",
        "date": " 3/20",
        "href": "https://www.ptt.cc/bbs/NBA/M.1710909689.A.9CA.html",
        "push_count": "47",
        "title": "[花邊] NBA LP將於直播中導入運彩賠率"
    },
    {
        "author": "sampsonlu919",
        "date": " 3/20",
        "href": "https://www.ptt.cc/bbs/NBA/M.1710866020.A.484.html",
        "push_count": "24",
        "title": "[情報] 巫師新秀Coulibaly右手腕骨折，本季報銷"
    },
    {
        "author": "jack34031",
        "date": " 3/20",
        "href": "https://www.ptt.cc/bbs/NBA/M.1710869709.A.455.html",
        "push_count": "16",
        "title": "[情報] Donovan Mitchell 接受鼻骨折手術"
    },
    {
        "author": "EZ78",
        "date": " 3/20",
        "href": "https://www.ptt.cc/bbs/NBA/M.1710871062.A.9D8.html",
        "push_count": "90",
        "title": "[情報] 賽爾提克勝分差超越16-17勇士"
    },
    {
        "author": "EZ78",
        "date": " 3/20",
        "href": "https://www.ptt.cc/bbs/NBA/M.1710872029.A.AB9.html",
        "push_count": "30",
        "title": "[花邊] Anthony Edwards因為對Collins的灌籃手指脫臼"
    },
    {
        "author": "jason911152",
        "date": " 3/20",
        "href": "https://www.ptt.cc/bbs/NBA/M.1710887422.A.14B.html",
        "push_count": "6",
        "title": "[Live] 火箭 @ 巫師"
    },
    {
        "author": "jason911152",
        "date": " 3/20",
        "href": "https://www.ptt.cc/bbs/NBA/M.1710888453.A.DF9.html",
        "push_count": "8",
        "title": "[Live] 黃蜂 @ 魔術"
    },
    {
        "author": "jason911152",
        "date": " 3/20",
        "href": "https://www.ptt.cc/bbs/NBA/M.1710889223.A.0AF.html",
        "push_count": "1",
        "title": "[Live] 鵜鶘 @ 籃網"
    },
    {
        "author": "jason911152",
        "date": " 3/20",
        "href": "https://www.ptt.cc/bbs/NBA/M.1710891021.A.203.html",
        "push_count": "爆",
        "title": "[Live] 獨行俠 @ 馬刺"
    },
    {
        "author": "thnlkj0665",
        "date": " 3/20",
        "href": "https://www.ptt.cc/bbs/NBA/M.1710893775.A.111.html",
        "push_count": "77",
        "title": "[花邊] 巴黎奧運男籃分組出爐  美國隊分在C組"
    }
]